{"a":[{"GrassesBorn":0,"GrassEatersBorn":24,"GishatichsBorn":1},{"GrassesBorn":0,"GrassEatersBorn":68,"GishatichsBorn":4},{"GrassesBorn":471,"GrassEatersBorn":215,"GishatichsBorn":5},{"GrassesBorn":697,"GrassEatersBorn":360,"GishatichsBorn":10},{"GrassesBorn":1019,"GrassEatersBorn":741,"GishatichsBorn":17},{"GrassesBorn":1305,"GrassEatersBorn":1012,"GishatichsBorn":37},{"GrassesBorn":1421,"GrassEatersBorn":1268,"GishatichsBorn":49},{"GrassesBorn":1421,"GrassEatersBorn":1294,"GishatichsBorn":49},{"GrassesBorn":1893,"GrassEatersBorn":1333,"GishatichsBorn":49},{"GrassesBorn":2051,"GrassEatersBorn":1341,"GishatichsBorn":49},{"GrassesBorn":2229,"GrassEatersBorn":1397,"GishatichsBorn":49},{"GrassesBorn":2432,"GrassEatersBorn":1466,"GishatichsBorn":49},{"GrassesBorn":2684,"GrassEatersBorn":1548,"GishatichsBorn":49},{"GrassesBorn":2937,"GrassEatersBorn":1728,"GishatichsBorn":52},{"GrassesBorn":3263,"GrassEatersBorn":2113,"GishatichsBorn":57},{"GrassesBorn":3564,"GrassEatersBorn":2390,"GishatichsBorn":68},{"GrassesBorn":3890,"GrassEatersBorn":2800,"GishatichsBorn":88},{"GrassesBorn":4160,"GrassEatersBorn":3063,"GishatichsBorn":100},{"GrassesBorn":4321,"GrassEatersBorn":3299,"GishatichsBorn":126},{"GrassesBorn":4479,"GrassEatersBorn":3469,"GishatichsBorn":152},{"GrassesBorn":4594,"GrassEatersBorn":3485,"GishatichsBorn":152},{"GrassesBorn":4676,"GrassEatersBorn":3523,"GishatichsBorn":153},{"GrassesBorn":4742,"GrassEatersBorn":3543,"GishatichsBorn":153},{"GrassesBorn":4808,"GrassEatersBorn":3565,"GishatichsBorn":154},{"GrassesBorn":4872,"GrassEatersBorn":3586,"GishatichsBorn":155},{"GrassesBorn":4918,"GrassEatersBorn":3594,"GishatichsBorn":156},{"GrassesBorn":4969,"GrassEatersBorn":3613,"GishatichsBorn":159},{"GrassesBorn":5014,"GrassEatersBorn":3635,"GishatichsBorn":163},{"GrassesBorn":5056,"GrassEatersBorn":3656,"GishatichsBorn":172},{"GrassesBorn":5099,"GrassEatersBorn":3660,"GishatichsBorn":172},{"GrassesBorn":5160,"GrassEatersBorn":3667,"GishatichsBorn":172},{"GrassesBorn":5232,"GrassEatersBorn":3682,"GishatichsBorn":175},{"GrassesBorn":5310,"GrassEatersBorn":3712,"GishatichsBorn":182},{"GrassesBorn":5379,"GrassEatersBorn":3722,"GishatichsBorn":183},{"GrassesBorn":5461,"GrassEatersBorn":3732,"GishatichsBorn":183},{"GrassesBorn":5533,"GrassEatersBorn":3739,"GishatichsBorn":183},{"GrassesBorn":5611,"GrassEatersBorn":3743,"GishatichsBorn":183},{"GrassesBorn":5673,"GrassEatersBorn":3751,"GishatichsBorn":183},{"GrassesBorn":5748,"GrassEatersBorn":3765,"GishatichsBorn":183}]}